odoo/addons/web_view_searchpanel/README.rst
odoo/addons/web_view_searchpanel/__init__.py
odoo/addons/web_view_searchpanel/__manifest__.py
odoo/addons/web_view_searchpanel/demo/res_users_views.xml
odoo/addons/web_view_searchpanel/i18n/web_view_searchpanel.pot
odoo/addons/web_view_searchpanel/models/__init__.py
odoo/addons/web_view_searchpanel/models/base.py
odoo/addons/web_view_searchpanel/readme/CONTRIBUTORS.rst
odoo/addons/web_view_searchpanel/readme/DESCRIPTION.rst
odoo/addons/web_view_searchpanel/readme/USAGE.rst
odoo/addons/web_view_searchpanel/static/description/icon.png
odoo/addons/web_view_searchpanel/static/description/index.html
odoo/addons/web_view_searchpanel/static/src/js/kanban_controller.js
odoo/addons/web_view_searchpanel/static/src/js/kanban_renderer.js
odoo/addons/web_view_searchpanel/static/src/js/kanban_searchpanel.js
odoo/addons/web_view_searchpanel/static/src/js/kanban_view.js
odoo/addons/web_view_searchpanel/static/src/scss/kanban_view.scss
odoo/addons/web_view_searchpanel/static/src/scss/variables.scss
odoo/addons/web_view_searchpanel/static/src/xml/kanban.xml
odoo/addons/web_view_searchpanel/template/assets.xml
odoo12_addon_web_view_searchpanel-12.0.1.0.2.dist-info/METADATA
odoo12_addon_web_view_searchpanel-12.0.1.0.2.dist-info/WHEEL
odoo12_addon_web_view_searchpanel-12.0.1.0.2.dist-info/top_level.txt
odoo12_addon_web_view_searchpanel-12.0.1.0.2.dist-info/RECORD
