Metadata-Version: 2.1
Name: odoo12-addon-web-view-searchpanel
Version: 12.0.1.0.2
Summary: Kanban Search Panel
Home-page: https://github.com/OCA/web
Author: MuK IT, Odoo Community Association (OCA)
Author-email: support@odoo-community.org
License: LGPL-3
Platform: UNKNOWN
Classifier: Programming Language :: Python
Classifier: Framework :: Odoo
Classifier: License :: OSI Approved :: GNU Lesser General Public License v3 (LGPLv3)
Requires-Python: >=3.5
Requires-Dist: odoo (<12.1dev,>=12.0a)
